moliere/__init__.py
Moliere-0.0.8.dist-info/LICENSE
Moliere-0.0.8.dist-info/METADATA
Moliere-0.0.8.dist-info/WHEEL
Moliere-0.0.8.dist-info/top_level.txt
Moliere-0.0.8.dist-info/RECORD
