Metadata-Version: 2.1
Name: Moliere
Version: 0.0.8
Summary: Psycopg wrapper
Home-page: https://gitlab.com/pmenshih/moliere
Author: Peter Menshih
Author-email: p.menshih@gmail.com
Classifier: Programming Language :: Python :: 3
Classifier: License :: OSI Approved :: MIT License
Classifier: Operating System :: OS Independent
Requires-Python: >=3.7
License-File: LICENSE
Requires-Dist: psycopg2-binary
Requires-Dist: python-dotenv
